{
  "prompts": [
    "Create a ghost-type Pokemon that resembles a jellyfish with a haunting appearance.",
    "I want a vibrant blue water-type Pokemon that floats elegantly in the ocean.",
    "Generate a playful Pokemon with a round body and tentacles, perfect for underwater adventures.",
    "Make a spooky jellyfish Pokemon with glowing features and a mysterious aura.",
    "Imagine a unique Pokemon that can change colors, combining shades of blue and white.",
    "Design a water/ghost-type Pokemon that loves to play tricks on unsuspecting trainers.",
    "Show me a Pokemon that embodies the essence of the sea and has a whimsical form."
  ],
  "visual_attributes": {
    "primary_colors": [
      "Blue",
      "White"
    ],
    "secondary_colors": [],
    "color_distribution": {
      "primary": "Blue",
      "secondary": null,
      "accent": "White"
    },
    "body_shape": "Amorphous",
    "size_class": "Medium",
    "distinctive_features": [
      "Jellyfish-like body",
      "Floating appearance",
      "Tentacle-like appendages",
      "Translucent bell shape",
      "Facial expression resembling a smile"
    ]
  },
  "categorical_attributes": {
    "type1": "Water",
    "type2": "Ghost",
    "generation": 5,
    "is_legendary": false,
    "is_mythical": false,
    "is_starter": false,
    "evolution_stage": "Final"
  },
  "semantic_attributes": {
    "personality_traits": [
      "Mischievous",
      "Playful",
      "Mysterious"
    ],
    "habitat": "Sea",
    "rarity": "Rare",
    "combat_style": "Special Attacker"
  },
  "image_path": "images/Jellicent/3.png",
  "pokemon_name": "Jellicent"
}